[
  {
    "id": 1,
    "category": "milk",
    "date": "2023-03-01",
    "time": "17:40:07",
    "recorder": "father",
    "volume": 140,
    "big": "",
    "email": "archihw94@gmail.com"
  },
  {
    "id": 2,
    "category": "diaper",
    "date": "2023-03-02",
    "time": "17:30:07",
    "recorder": "mother",
    "volume": "",
    "big": "small",
    "email": "archihw94@gmail.com"
  },
  {
    "id": 3,
    "category": "sleep",
    "date": "2023-03-03",
    "time": "18:40:17",
    "recorder": "father",
    "volume": "",
    "big": "",
    "email": "archihw94@gmail.com"
  },
  {
    "id": 4,
    "category": "milk",
    "date": "2023-03-04",
    "time": "20:40:07",
    "recorder": "father",
    "volume": 140,
    "big": "",
    "email": "archihw94@gmail.com"
  },
  {
    "id": 5,
    "category": "milk",
    "date": "2023-03-04",
    "time": "17:40:07",
    "recorder": "father",
    "volume": 140,
    "big": "",
    "email": "archihw94@gmail.com"
  },
  {
    "id": 6,
    "category": "milk",
    "date": "2023-03-04",
    "time": "17:40:07",
    "recorder": "father",
    "volume": 140,
    "big": "",
    "email": "archihw94@gmail.com"
  },
  {
    "id": 7,
    "category": "milk",
    "date": "2023-03-05",
    "time": "17:40:07",
    "recorder": "father",
    "volume": 140,
    "big": "",
    "email": "archihw94@gmail.com"
  },
  {
    "id": 8,
    "category": "milk",
    "date": "2023-03-06",
    "time": "17:40:07",
    "recorder": "father",
    "volume": 140,
    "big": "",
    "email": "archihw94@gmail.com"
  },
  {
    "id": 9,
    "category": "milk",
    "date": "2023-03-06",
    "time": "17:40:07",
    "recorder": "father",
    "volume": 140,
    "big": "",
    "email": "archihw94@gmail.com"
  },
  {
    "id": 10,
    "category": "sleep",
    "date": "2023-03-06",
    "time": "13:40:07",
    "recorder": "father",
    "volume": 140,
    "big": "",
    "email": "archihw94@gmail.com"
  },
  {
    "id": 10,
    "category": "sleep",
    "date": "2023-03-06",
    "time": "13:40:07",
    "recorder": "father",
    "volume": 140,
    "big": "",
    "email": "archihw94@gmail.com"
  },
  {
    "id": 10,
    "category": "milk",
    "date": "2023-02-06",
    "time": "17:40:07",
    "recorder": "father",
    "volume": 140,
    "big": "",
    "email": "archihw94@gmail.com"
  },
  {
    "id": 10,
    "category": "milk",
    "date": "2023-03-06",
    "time": "23:00:00",
    "recorder": "father",
    "volume": 140,
    "big": "",
    "email": "archihw94@gmail.com"
  },
  {
    "id": 10,
    "category": "sleep",
    "date": "2023-03-06",
    "time": "23:30:00",
    "recorder": "father",
    "volume": "",
    "big": "",
    "email": "archihw94@gmail.com"
  },
  {
    "id": 10,
    "category": "milk",
    "date": "2023-03-07",
    "time": "04:59:00",
    "recorder": "father",
    "volume": "140",
    "big": "",
    "email": "archihw94@gmail.com"
  },
  {
    "id": 10,
    "category": "milk",
    "date": "2023-03-07",
    "time": "09:10:00",
    "recorder": "mother",
    "volume": "140",
    "big": "",
    "email": "archihw94@gmail.com"
  },
  {
    "id": 10,
    "category": "milk",
    "date": "2023-03-07",
    "time": "12:09:00",
    "recorder": "father",
    "volume": "140",
    "big": "",
    "email": "archihw94@gmail.com"
  },
  {
    "id": 10,
    "category": "milk",
    "date": "2023-03-07",
    "time": "21:39:00",
    "recorder": "mother",
    "volume": "200",
    "big": "",
    "email": "archihw94@gmail.com"
  },
  {
    "id": 10,
    "category": "milk",
    "date": "2023-03-07",
    "time": "12:09:00",
    "recorder": "father",
    "volume": "140",
    "big": "",
    "email": "archihw94@gmail.com"
  },
  {
    "id": 10,
    "category": "milk",
    "date": "2023-03-07",
    "time": "12:09:00",
    "recorder": "mother",
    "volume": "140",
    "big": "",
    "email": "archihw94@gmail.com"
  },
  {
    "id": 10,
    "category": "milk",
    "date": "2023-03-07",
    "time": "12:09:00",
    "recorder": "father",
    "volume": "140",
    "big": "",
    "email": "archihw94@gmail.com"
  },
  {
    "id": 10,
    "category": "milk",
    "date": "2023-03-07",
    "time": "12:09:00",
    "recorder": "father",
    "volume": "140",
    "big": "",
    "email": "archihw94@gmail.com"
  },
  {
    "id": 10,
    "category": "milk",
    "date": "2023-03-07",
    "time": "21:39:00",
    "recorder": "mother",
    "volume": "140",
    "big": "",
    "email": "archihw94@gmail.com"
  },
  {
    "id": 10,
    "category": "sleep",
    "date": "2023-03-07",
    "time": "23:30:00",
    "recorder": "mother",
    "volume": "",
    "big": "",
    "email": "archihw94@gmail.com"
  }
]
